koturn/__init__.py
koturn/config.py
koturn/definitions.py
koturn/env.py
koturn/exp.py
koturn/models.py
koturn/rtc_ice_server.py
koturn/db/__init__.py
koturn/db/dynamo_db.py
koturn/db/dynamo_table.py
koturn/db/koturn_instance_table.py
koturn/db/table.py
koturn/protocols/__init__.py
koturn/protocols/protocol.py
koturn/protocols/stun.py
koturn/protocols/turn.py
koturn-0.0.1.dist-info/METADATA
koturn-0.0.1.dist-info/WHEEL
koturn-0.0.1.dist-info/top_level.txt
koturn-0.0.1.dist-info/RECORD
