Metadata-Version: 2.1
Name: koturn
Version: 0.0.1
Summary: Koturn Python Client
Home-page: https://github.com/whittlbc/koturn-py
Author: Ben Whittle
Author-email: benwhittle31@gmail.com
License: MIT
Platform: UNKNOWN
Requires-Dist: boto3 (==1.17.22)
